CHANGES.rst
CONTRIBUTORS.rst
DEVELOP.rst
LICENSE.GPL
LICENSE.rst
MANIFEST.in
README.rst
requirements.txt
setup.cfg
setup.py
docs/index.rst
src/collective/__init__.py
src/collective.behavior.richdescription.egg-info/PKG-INFO
src/collective.behavior.richdescription.egg-info/SOURCES.txt
src/collective.behavior.richdescription.egg-info/dependency_links.txt
src/collective.behavior.richdescription.egg-info/entry_points.txt
src/collective.behavior.richdescription.egg-info/namespace_packages.txt
src/collective.behavior.richdescription.egg-info/not-zip-safe
src/collective.behavior.richdescription.egg-info/requires.txt
src/collective.behavior.richdescription.egg-info/top_level.txt
src/collective/behavior/__init__.py
src/collective/behavior/richdescription/__init__.py
src/collective/behavior/richdescription/behavior.py
src/collective/behavior/richdescription/configure.zcml
src/collective/behavior/richdescription/locales/collective.behavior.richdescription.pot
src/collective/behavior/richdescription/locales/update.sh
src/collective/behavior/richdescription/locales/fr/LC_MESSAGES/collective.behavior.richdescription.po
src/collective/behavior/richdescription/viewlet/__init__.py
src/collective/behavior/richdescription/viewlet/configure.zcml
src/collective/behavior/richdescription/viewlet/rich_description.py
src/collective/behavior/richdescription/viewlet/templates/rich_description.pt