Metadata-Version: 1.1
Name: collective.behavior.richdescription
Version: 1.0a1
Summary: A rich description behavior and viewlet for Dexterity
Home-page: https://pypi.python.org/pypi/collective.behavior.richdescription
Author: Martin Peeters
Author-email: support@imio.be
License: GPL version 2
Keywords: Python Plone
Platform: UNKNOWN
Classifier: Environment :: Web Environment
Classifier: Framework :: Plone
Classifier: Framework :: Plone :: 4.3
Classifier: Programming Language :: Python
Classifier: Programming Language :: Python :: 2.7
Classifier: Operating System :: OS Independent
Classifier: License :: OSI Approved :: GNU General Public License v2 (GPLv2)
